<?xml version="1.0" encoding="UTF-8"?>

<persistence version="2.0"
	xmlns="http://java.sun.com/xml/ns/persistence" xmlns:xsi="http://www.w3.org/2001/XMLSchema-instance"
	xsi:schemaLocation="http://java.sun.com/xml/ns/persistence http://java.sun.com/xml/ns/persistence/persistence_2_0.xsd">
	<persistence-unit name="movieBook">
		<provider>org.hibernate.ejb.HibernatePersistence</provider>
		<class>com.daniel.models.Movie</class>
		<!-- <properties>
			<property name="hibernate.connection.url" value="jdbc:mysql://localhost:3306/danieldb" />
			<property name="hibernate.connection.driver_class" value="com.mysql.jdbc.Driver" />
			<property name="hibernate.connection.username" value="root" />
			<property name="hibernate.connection.password" value="daniel10" />
			<property name="hibernate.dialect" value="org.hibernate.dialect.MySQL5Dialect" />
			<property name="hibernate.hbm2ddl.auto" value="update" />
			<property name="hibernate.current_session_context_class"
				value="thread" />
			<property name="hibernate.show_sql" value="true" />
			
			<property name="jaxa.persistence.jdbc.url" value="jdbc:mysql://localhost:3306/danieldb" />
			<property name="javax.persistence.jdbc.driver" value="com.mysql.jdbc.Driver" />
			<property name="javax.persistence.jdbc.user" value="root" />
			<property name="javax.persistence.jdbc.password" value="daniel10" />
			
		</properties>
		-->
	</persistence-unit>
</persistence>